ava/__init__.py
ava/ava.py
ava/cli.py
ava/utilities.py
avacli-3.1.dist-info/LICENSE
avacli-3.1.dist-info/METADATA
avacli-3.1.dist-info/WHEEL
avacli-3.1.dist-info/entry_points.txt
avacli-3.1.dist-info/top_level.txt
avacli-3.1.dist-info/RECORD
