Metadata-Version: 2.1
Name: avacli
Version: 3.1
Summary: UNKNOWN
Home-page: https://github.com/ZakHargz/ava-cli
Author: Zak Hargreaves
Author-email: zak@hargreaves.xyz
License: UNKNOWN
Platform: UNKNOWN
Classifier: Development Status :: 4 - Beta
Classifier: Programming Language :: Python :: 3.8
Classifier: License :: OSI Approved :: GNU General Public License v3 (GPLv3)
Requires-Dist: click (==7.1.2)
Requires-Dist: PyGithub (==1.54.1)
Requires-Dist: boto3 (==1.17.0)
Requires-Dist: rich (==9.10.0)
